neuron/hclass3.py
neuron/expect_hocerr.py
neuron/psection.py
neuron/config.py
neuron/units.py
neuron/sections.py
neuron/__init__.py
neuron/hoc.cpython-39-darwin.so
neuron/coreneuron.py
neuron/doc.py
neuron/help_data.dat
neuron/gui.py
neuron/nonvint_block_supervisor.py
neuron/neuroml/metadata.py
neuron/neuroml/morphml.py
neuron/neuroml/xml2nrn.py
neuron/neuroml/__init__.py
neuron/neuroml/neuroml.py
neuron/neuroml/rdxml.py
neuron/neuroml/biophysics.py
neuron/rxd/rxdException.py
neuron/rxd/options.py
neuron/rxd/plugins.py
neuron/rxd/rxdsection.py
neuron/rxd/species.py
neuron/rxd/rxdmath.py
neuron/rxd/rate.py
neuron/rxd/region.py
neuron/rxd/multiCompartmentReaction.py
neuron/rxd/constants.py
neuron/rxd/dimension3.py
neuron/rxd/__init__.py
neuron/rxd/section1d.py
neuron/rxd/export.py
neuron/rxd/initializer.py
neuron/rxd/rangevar.py
neuron/rxd/geometry.py
neuron/rxd/rxd.py
neuron/rxd/generalizedReaction.py
neuron/rxd/nodelist.py
neuron/rxd/node.py
neuron/rxd/gui.py
neuron/rxd/reaction.py
neuron/rxd/geometry3d/surfaces.cpython-39-darwin.so
neuron/rxd/geometry3d/ctng.cpython-39-darwin.so
neuron/rxd/geometry3d/simplevolume_helper.py
neuron/rxd/geometry3d/GeneralizedVoxelization.py
neuron/rxd/geometry3d/FullJoinMorph.py
neuron/rxd/geometry3d/scalarField.py
neuron/rxd/geometry3d/__init__.py
neuron/rxd/geometry3d/surface_a.py
neuron/rxd/geometry3d/graphicsPrimitives.cpython-39-darwin.so
neuron/rxd/geometry3d/triangularMesh.py
neuron/rxd/geometry3d/voxelize.py
neuron/rxd/geometry3d/voxelize2.py
neuron/rxd/geometry3d/surface.py
neuron/tests/_subclass.py
neuron/tests/test_all.py
neuron/tests/__init__.py
neuron/tests/test_neuron.py
neuron/tests/test_vector.py
neuron/tests/test_rxd.py
neuron/tests/utils/__init__.py
neuron/tests/utils/strtobool.py
neuron/tests/utils/checkresult.py
neuron/.dylibs/libxcb.1.dylib
neuron/.dylibs/libnrniv.dylib
neuron/.dylibs/libICE.6.dylib
neuron/.dylibs/libX11.6.dylib
NEURON_nightly-9.0.dev1289.dist-info/RECORD
NEURON_nightly-9.0.dev1289.dist-info/WHEEL
NEURON_nightly-9.0.dev1289.dist-info/top_level.txt
NEURON_nightly-9.0.dev1289.dist-info/METADATA
